brainstem_api_tools/__init__.py
brainstem_api_tools/brainstem_api_client.py
brainstem_python_api_tools-0.2.0.dist-info/LICENSE
brainstem_python_api_tools-0.2.0.dist-info/METADATA
brainstem_python_api_tools-0.2.0.dist-info/WHEEL
brainstem_python_api_tools-0.2.0.dist-info/top_level.txt
brainstem_python_api_tools-0.2.0.dist-info/RECORD
