Metadata-Version: 2.1
Name: brainstem_python_api_tools
Version: 0.2.0
Summary: A Python toolset for interacting with API of BrainSTEM.
Home-page: https://github.com/brainstem-org/brainstem_python_api_tools
Author: BrainSTEM Team
Author-email: petersen.peter@gmail.com
License: MIT
Classifier: Programming Language :: Python :: 3
Classifier: License :: OSI Approved :: MIT License
Classifier: Operating System :: OS Independent
Requires-Python: >=3.7
License-File: LICENSE
Requires-Dist: requests
Requires-Dist: jupyter
